plank/logger/__init__.py
plank_tool_logger-0.1.0.dist-info/LICENSE
plank_tool_logger-0.1.0.dist-info/WHEEL
plank_tool_logger-0.1.0.dist-info/METADATA
plank_tool_logger-0.1.0.dist-info/RECORD
