Metadata-Version: 2.1
Name: plank-tool-logger
Version: 0.1.0
Summary: The logger tool of plank project.
Author: Grady Zhuo
Author-email: grady@ospark.org
Requires-Python: >=3.8,<4.0
Classifier: Programming Language :: Python :: 3
Classifier: Programming Language :: Python :: 3.8
Classifier: Programming Language :: Python :: 3.9
Classifier: Programming Language :: Python :: 3.10
Classifier: Programming Language :: Python :: 3.11
